Metadata-Version: 2.1
Name: spnets
Version: 0.0.0
Summary: A spatiotemporal network benchmark.
Home-page: https://github.com/yrqUni
Author: yrqUni
Author-email: yrqUni@gmail.com
License: MIT License
Keywords: SA-ConvLSTM,PredRNN,Spatiotemporal
Platform: UNKNOWN
